pilmoji/__init__.py
pilmoji/core.py
pilmoji/helpers.py
pilmoji/source.py
pilmoji-2.0.5.dist-info/licenses/LICENSE
pilmoji-2.0.5.dist-info/METADATA
pilmoji-2.0.5.dist-info/WHEEL
pilmoji-2.0.5.dist-info/top_level.txt
pilmoji-2.0.5.dist-info/RECORD
