Metadata-Version: 2.1
Name: pilmoji
Version: 2.0.5
Summary: Pilmoji is an emoji renderer for Pillow, Python's imaging library.
Home-page: https://github.com/jay3332/pilmoji
Author: jay3332
License: MIT
Project-URL: Issue tracker, https://github.com/jay3332/pilmoji
Project-URL: Discord, https://discord.gg/FqtZ6akWpd
Classifier: License :: OSI Approved :: MIT License
Classifier: Intended Audience :: Developers
Classifier: Natural Language :: English
Classifier: Operating System :: OS Independent
Classifier: Programming Language :: Python :: 3.8
Classifier: Programming Language :: Python :: 3.9
Classifier: Topic :: Internet
Classifier: Topic :: Software Development :: Libraries
Classifier: Topic :: Software Development :: Libraries :: Python Modules
Classifier: Topic :: Utilities
Requires-Python: >=3.8.0
Provides-Extra: requests
License-File: LICENSE
